predictionserver/__init__.py
predictionserver-0.0.1.dist-info/LICENSE
predictionserver-0.0.1.dist-info/METADATA
predictionserver-0.0.1.dist-info/WHEEL
predictionserver-0.0.1.dist-info/entry_points.txt
predictionserver-0.0.1.dist-info/top_level.txt
predictionserver-0.0.1.dist-info/RECORD
