Metadata-Version: 2.1
Name: predictionserver
Version: 0.0.1
Summary: Powering community nowcasts at www.microprediction.org
Home-page: https://github.com/microprediction/predictionserver
Author: microprediction
Author-email: pcotton@intechinvestments.com
License: MIT
Platform: UNKNOWN
Classifier: License :: OSI Approved :: MIT License
Classifier: Programming Language :: Python :: 3
Classifier: Programming Language :: Python :: 3.7
Requires-Dist: fakeredis
Requires-Dist: getjson
Requires-Dist: redis
Requires-Dist: sortedcontainers
Requires-Dist: numpy
Requires-Dist: pymorton
Requires-Dist: scipy
Requires-Dist: pathlib
Requires-Dist: plotly (>=4.9.0)
Requires-Dist: muid
Requires-Dist: requests
Requires-Dist: tdigest
Requires-Dist: flask
Requires-Dist: flask-application
